odoo/addons/product_price_history/README.rst
odoo/addons/product_price_history/__init__.py
odoo/addons/product_price_history/__manifest__.py
odoo/addons/product_price_history/i18n/fr.po
odoo/addons/product_price_history/i18n/it.po
odoo/addons/product_price_history/i18n/product_price_history.pot
odoo/addons/product_price_history/models/__init__.py
odoo/addons/product_price_history/models/product_price_history.py
odoo/addons/product_price_history/models/product_product.py
odoo/addons/product_price_history/models/product_template.py
odoo/addons/product_price_history/readme/CONTRIBUTORS.rst
odoo/addons/product_price_history/readme/DESCRIPTION.rst
odoo/addons/product_price_history/readme/HISTORY.rst
odoo/addons/product_price_history/readme/USAGE.rst
odoo/addons/product_price_history/static/description/icon.png
odoo/addons/product_price_history/static/description/index.html
odoo/addons/product_price_history/static/description/product_price_history_graph.png
odoo/addons/product_price_history/views/product_price_history_view.xml
odoo12_addon_product_price_history-12.0.1.0.1.dist-info/METADATA
odoo12_addon_product_price_history-12.0.1.0.1.dist-info/WHEEL
odoo12_addon_product_price_history-12.0.1.0.1.dist-info/top_level.txt
odoo12_addon_product_price_history-12.0.1.0.1.dist-info/RECORD
